cmakegenerators/__init__.py
cmakegenerators/generators.py
cmake_generators-1.0.9.dist-info/LICENSE
cmake_generators-1.0.9.dist-info/METADATA
cmake_generators-1.0.9.dist-info/WHEEL
cmake_generators-1.0.9.dist-info/top_level.txt
cmake_generators-1.0.9.dist-info/RECORD
